servian_vertex_components/__init__.py
servian_vertex_components/components.py
servian_vertex_components/workflow.py
servian_vertex_components-0.1.0.dist-info/LICENSE
servian_vertex_components-0.1.0.dist-info/METADATA
servian_vertex_components-0.1.0.dist-info/WHEEL
servian_vertex_components-0.1.0.dist-info/top_level.txt
servian_vertex_components-0.1.0.dist-info/RECORD
